puan_solvers/__init__.py
tests/__init__.py
tests/test_puan_solver.py
puan_solvers-0.0.3.dist-info/LICENSE
puan_solvers-0.0.3.dist-info/METADATA
puan_solvers-0.0.3.dist-info/WHEEL
puan_solvers-0.0.3.dist-info/top_level.txt
puan_solvers-0.0.3.dist-info/RECORD
